[
    { 
        "company": "AIT Solutions",
        "icon": "res/aits.png",
        "address": "Asian Institute of Technology, Bangkok, Thailand",
        "title": "JavaScript Developer",
        "description": ""
    },
    { 
        "company": "AIT Solutions",
        "icon": "res/aits.png",
        "address": "Asian Institute of Technology, Bangkok, Thailand",
        "title": "NodeJS Developer",
        "description": ""
    },
    { 
        "company": "AIT Solutions",
        "icon": "res/aits.png",
        "address": "Asian Institute of Technology, Bangkok, Thailand",
        "title": "C# Developer",
        "description": ""
    }
]